MANIFEST.in
README.rst
setup.py
terraref/__init__.py
terraref/stereo_rgb/__init__.py
terraref/stereo_rgb/stereo_rgb.py
terraref_stereo_rgb.egg-info/PKG-INFO
terraref_stereo_rgb.egg-info/SOURCES.txt
terraref_stereo_rgb.egg-info/dependency_links.txt
terraref_stereo_rgb.egg-info/namespace_packages.txt
terraref_stereo_rgb.egg-info/requires.txt
terraref_stereo_rgb.egg-info/top_level.txt
tests/data/.DS_Store
tests/data/binfile.bin
tests/data/metadata.json