Metadata-Version: 1.0
Name: terraref-stereo-rgb
Version: 1.0.4
Summary: TERRA-REF stereo RGB camera science package
Home-page: https://github.com/terraref/stereo_rgb
Author: UNKNOWN
Author-email: UNKNOWN
License: UNKNOWN
Platform: UNKNOWN
